acbrlib_python/__init__.py
acbrlib_python/cep/__init__.py
acbrlib_python/cep/constantes.py
acbrlib_python/cep/excecoes.py
acbrlib_python/cep/impl.py
acbrlib_python/cep/modelos.py
acbrlib_python/constantes.py
acbrlib_python/excecoes.py
acbrlib_python/mixins.py
acbrlib_python/proto.py
acbrlib_python-0.1.0.dist-info/LICENSE
acbrlib_python-0.1.0.dist-info/WHEEL
acbrlib_python-0.1.0.dist-info/METADATA
acbrlib_python-0.1.0.dist-info/RECORD
