Metadata-Version: 2.1
Name: acbrlib-python
Version: 0.1.0
Summary: Camada de abstração para acesso à ACBrLib em Python
Home-page: https://github.com/base4sistemas/acbrlib-python
License: Apache-2.0
Author: Daniel Gonçalves
Author-email: daniel@base4.com.br
Requires-Python: >=3.9,<4.0
Classifier: Development Status :: 1 - Planning
Classifier: Environment :: Other Environment
Classifier: Intended Audience :: Developers
Classifier: License :: OSI Approved :: Apache Software License
Classifier: Natural Language :: Portuguese (Brazilian)
Classifier: Operating System :: OS Independent
Classifier: Programming Language :: Python
Classifier: Programming Language :: Python :: 3
Classifier: Programming Language :: Python :: 3.9
Classifier: Topic :: Office/Business
Classifier: Topic :: Office/Business :: Financial
Classifier: Topic :: Office/Business :: Financial :: Point-Of-Sale
Classifier: Topic :: Printing
Classifier: Topic :: Software Development
Classifier: Topic :: Software Development :: Libraries
Requires-Dist: Unidecode (>=1.3.2,<2.0.0)
Project-URL: Bug Tracker, https://github.com/base4sistemas/acbrlib-python/issues
Project-URL: Repository, https://github.com/base4sistemas/acbrlib-python
